{
  "main": {
    "id": "c41fd8910d1c50ec",
    "type": "split",
    "children": [
      {
        "id": "ff2481dc46b9b649",
        "type": "tabs",
        "children": [
          {
            "id": "44fb61f50dde1d32",
            "type": "leaf",
            "state": {
              "type": "markdown",
              "state": {
                "file": "daily/2024/June/30 June 2024.md",
                "mode": "preview",
                "backlinks": false,
                "source": true
              }
            }
          }
        ]
      }
    ],
    "direction": "vertical"
  },
  "left": {
    "id": "6ec7fd19e3ffbfef",
    "type": "split",
    "children": [
      {
        "id": "c0c953456da8b7b7",
        "type": "tabs",
        "children": [
          {
            "id": "f1749076adb04809",
            "type": "leaf",
            "state": {
              "type": "file-explorer",
              "state": {
                "sortOrder": "alphabetical"
              }
            }
          },
          {
            "id": "20c6e13261f78014",
            "type": "leaf",
            "state": {
              "type": "git-history-view",
              "state": {}
            }
          },
          {
            "id": "881652e5a5ee6058",
            "type": "leaf",
            "state": {
              "type": "outline",
              "state": {
                "file": "daily/2024/June/30 June 2024.md"
              }
            }
          },
          {
            "id": "aae7d89e6800d73d",
            "type": "leaf",
            "state": {
              "type": "tag",
              "state": {
                "sortOrder": "frequency",
                "useHierarchy": true
              }
            }
          }
        ]
      }
    ],
    "direction": "horizontal",
    "width": 301.50288009643555
  },
  "right": {
    "id": "050f07a396bd8acb",
    "type": "split",
    "children": [
      {
        "id": "ff098a09d76e69cc",
        "type": "tabs",
        "children": [
          {
            "id": "ad1f8644a00a8e47",
            "type": "leaf",
            "state": {
              "type": "search",
              "state": {
                "query": "async",
                "matchingCase": false,
                "explainSearch": false,
                "collapseAll": false,
                "extraContext": false,
                "sortOrder": "byModifiedTime"
              }
            }
          },
          {
            "id": "6a4b24fa63c0909c",
            "type": "leaf",
            "state": {
              "type": "backlink",
              "state": {
                "file": "daily/2024/June/30 June 2024.md",
                "collapseAll": false,
                "extraContext": false,
                "sortOrder": "alphabetical",
                "showSearch": false,
                "searchQuery": "",
                "backlinkCollapsed": false,
                "unlinkedCollapsed": true
              }
            }
          }
        ],
        "currentTab": 1
      }
    ],
    "direction": "horizontal",
    "width": 272.5,
    "collapsed": true
  },
  "left-ribbon": {
    "hiddenItems": {
      "publish:Publish changes...": false,
      "daily-notes:Open today's daily note": false,
      "graph:Open graph view": true,
      "switcher:Open quick switcher": true,
      "command-palette:Open command palette": true,
      "table-editor-obsidian:Advanced Tables Toolbar": true,
      "templater-obsidian:Templater": false
    }
  },
  "active": "f1749076adb04809",
  "lastOpenFiles": [
    "resources/templates/Template, Daily Note Section.md",
    "daily/2024/June/30 June 2024.md",
    "daily/2024/June/29 June 2024.md",
    "resources/templates/Template, Daily Note.md",
    "resources/templates/Template, Last Modified.md",
    "daily/2024/June/30 June 2026.md",
    "daily/2024/February/13 February 2024.md",
    "daily/2024/June/30 June 2025.md",
    "daily/2024/June/28 June 2024.md",
    "resources",
    "resources/templates",
    "daily/2024/June/11 June 2024.md",
    "daily/2024/June/20 June 2024.md",
    "daily/2024/June/21 June 2024.md",
    "daily/2024/June/18 June 2024.md",
    "daily/2024/June/30-06-2024-Sunday.md",
    "daily/2024/June/2024/June/30-06-2024-Sunday.md",
    "daily/2024/June/2024/June",
    "daily/2024/June/2024",
    "daily/2023/November/22 November 2023.md",
    "daily/2023/November/23 November 2023.md",
    "daily/2023/November/24 November 2023.md",
    "daily/2023/November/26 November 2023.md",
    "daily/2023/November/27 November 2023.md",
    "daily/2023/November/28 November 2023.md",
    "daily/2023/November/29 November 2023.md",
    "daily/2023/November/30 November 2023.md",
    "daily/2023/December/01 December 2023.md",
    "daily/2023/December/04 December 2023.md",
    "daily/2023/December/06 December 2023.md",
    "resources/assets/10 June 2024-20240610011604023.webp",
    "resources/assets/10 June 2024-20240610174706126.webp",
    "resources/assets/10 June 2024-20240610011427192.webp",
    "resources/assets/09 June 2024-20240609021548078.webp",
    "resources/assets/09 June 2024-20240609012450746.webp",
    "daily/2024/June",
    "resources/assets/28 May 2024-20240529021904576.webp",
    "resources/assets/28 May 2024-20240529021444945.webp",
    "resources/assets/28 May 2024-20240529021146933.webp",
    "resources/assets/28 May 2024-20240529020858609.webp",
    "daily/2024/May",
    "daily/2024/April",
    "daily/2024/March",
    "daily/2024/February",
    "daily/2024/January",
    "resources/assets/Miscellaneous notes on PHP-20240109132225023.webp",
    "Untitled.canvas",
    "my goo.canvas"
  ]
}